brcore/__init__.py
brcore/core.py
brcore/util.py
brcore/enum/__init__.py
brcore/enum/exception_texts.py
brcore/enum/channels/__init__.py
brcore/enum/channels/channel_argtype.py
brcore/enum/channels/channels.py
brominecore-1.1.dist-info/licenses/LICENSE
brominecore-1.1.dist-info/METADATA
brominecore-1.1.dist-info/WHEEL
brominecore-1.1.dist-info/top_level.txt
brominecore-1.1.dist-info/RECORD
