Metadata-Version: 2.4
Name: brominecore
Version: 1.1
Summary: Misskey websocketAPI wrapper.
Author: iodine53
Maintainer: iodine53
License: MIT License
Project-URL: Repository, https://github.com/35enidoi/BromineCore
Project-URL: Issues, https://github.com/35enidoi/BromineCore/issues
Keywords: misskey
Classifier: Development Status :: 5 - Production/Stable
Classifier: License :: OSI Approved :: MIT License
Classifier: Programming Language :: Python :: 3.10
Classifier: Programming Language :: Python :: 3.11
Classifier: Programming Language :: Python :: 3.12
Requires-Python: >=3.10
License-File: LICENSE
Requires-Dist: websockets
Requires-Dist: typing-extensions
Dynamic: license-file
